poisk/__init__.py
poisk/exceptions.py
poisk/many.py
poisk/one.py
poisk/pods.py
poisk/py.typed
poisk/types.py
test/__init__.py
test/test_poisk.py
test/test_readme_examples.py
test/test_type_checking.py
poisk-1.0.3.dist-info/LICENSE
poisk-1.0.3.dist-info/METADATA
poisk-1.0.3.dist-info/WHEEL
poisk-1.0.3.dist-info/top_level.txt
poisk-1.0.3.dist-info/RECORD
