Metadata-Version: 2.1
Name: poisk
Version: 1.0.3
Summary: Small utilities for searching data structures
Author: Hervé Saint-Amand
Author-email: poisk@saintamh.org
Classifier: License :: OSI Approved :: MIT License
Classifier: Operating System :: OS Independent
Classifier: Programming Language :: Python :: 3
License-File: LICENSE
Requires-Dist: cssselect <2,>=1.1
Requires-Dist: typing-extensions >=3.7
